picologging-0.9.3.dist-info/METADATA
picologging-0.9.3.dist-info/LICENSE
picologging-0.9.3.dist-info/WHEEL
picologging-0.9.3.dist-info/RECORD
picologging-0.9.3.dist-info/top_level.txt
picologging/_picologging.cpython-311-i386-linux-gnu.so
picologging/py.typed
picologging/__init__.pyi
picologging/config.pyi
picologging/handlers.pyi
picologging/config.py
picologging/handlers.py
picologging/__init__.py
