Metadata-Version: 2.1
Name: picologging
Version: 0.9.3
Summary: A fast and lightweight logging library for Python
Home-page: https://github.com/microsoft/picologging
Author: Microsoft
License: MIT License
Project-URL: Source, https://github.com/microsoft/picologging
Project-URL: Documentation, https://microsoft.github.io/picologging/
Classifier: Programming Language :: Python :: 3
Classifier: License :: OSI Approved :: MIT License
Classifier: Operating System :: OS Independent
Classifier: Development Status :: 4 - Beta
Classifier: Intended Audience :: Developers
Classifier: Topic :: System :: Logging
Classifier: Programming Language :: Python :: Implementation :: CPython
Classifier: Programming Language :: Python :: 3.7
Classifier: Programming Language :: Python :: 3.8
Classifier: Programming Language :: Python :: 3.9
Classifier: Programming Language :: Python :: 3.10
Classifier: Programming Language :: Python :: 3.11
Classifier: Programming Language :: Python :: 3.12
Requires-Python: >=3.7
License-File: LICENSE
Provides-Extra: dev
Requires-Dist: rich ; extra == 'dev'
Requires-Dist: pytest ; extra == 'dev'
Requires-Dist: pytest-cov ; extra == 'dev'
Requires-Dist: pytest-memray >=1.5.0 ; extra == 'dev'
Requires-Dist: hypothesis ; extra == 'dev'
Requires-Dist: flaky ; extra == 'dev'
Requires-Dist: black ; extra == 'dev'
Requires-Dist: pre-commit ; extra == 'dev'
